geocode_fallback_library.py
robust_geocoder-0.1.0.dist-info/METADATA
robust_geocoder-0.1.0.dist-info/WHEEL
robust_geocoder-0.1.0.dist-info/entry_points.txt
robust_geocoder-0.1.0.dist-info/top_level.txt
robust_geocoder-0.1.0.dist-info/RECORD
