Metadata-Version: 2.4
Name: robust-geocoder
Version: 0.1.0
Summary: A comprehensive geocoding library with multiple fallback providers and postal code lookup.
Home-page: https://github.com/raninduH/robust-geocoder
Author: Ranindu Harischandra
Author-email: raninduharischandra12@gmail.com
License: MIT
Keywords: geocoding,postal code,address lookup,location,coordinates,fallback,Sri Lanka,OpenStreetMap,photon,wikidata,duckduckgo,serper
Classifier: Programming Language :: Python :: 3
Classifier: License :: OSI Approved :: MIT License
Classifier: Operating System :: OS Independent
Requires-Python: >=3.7
Requires-Dist: pandas
Requires-Dist: pgeocode
Requires-Dist: requests
Requires-Dist: python-dotenv
Requires-Dist: geopy
Requires-Dist: concurrent-futures; python_version < "3.2"
Requires-Dist: SPARQLWrapper; extra == "wikidata"
Requires-Dist: duckduckgo-search; extra == "duckduckgo"
Provides-Extra: wikidata
Requires-Dist: SPARQLWrapper; extra == "wikidata"
Provides-Extra: duckduckgo
Requires-Dist: duckduckgo-search; extra == "duckduckgo"
Dynamic: author
Dynamic: author-email
Dynamic: classifier
Dynamic: description
Dynamic: description-content-type
Dynamic: home-page
Dynamic: keywords
Dynamic: license
Dynamic: provides-extra
Dynamic: requires-dist
Dynamic: requires-python
Dynamic: summary
